{
"meta":{"test_sets":[],"test_metrics":[],"learn_metrics":[{"best_value":"Min","name":"RMSE"}],"launch_mode":"Train","parameters":"","iteration_count":100,"learn_sets":["learn"],"name":"experiment"},
"iterations":[
{"learn":[14.005006],"iteration":0,"passed_time":0.0009870671373,"remaining_time":0.09771964659},
{"learn":[13.14441192],"iteration":1,"passed_time":0.001898437133,"remaining_time":0.0930234195},
{"learn":[12.34258257],"iteration":2,"passed_time":0.002822614029,"remaining_time":0.09126452029},
{"learn":[11.64527793],"iteration":3,"passed_time":0.003516736721,"remaining_time":0.0844016813},
{"learn":[11.02766183],"iteration":4,"passed_time":0.004565811325,"remaining_time":0.08675041517},
{"learn":[10.43485794],"iteration":5,"passed_time":0.005586101298,"remaining_time":0.087515587},
{"learn":[9.890641275],"iteration":6,"passed_time":0.006654976758,"remaining_time":0.08841611979},
{"learn":[9.492161212],"iteration":7,"passed_time":0.007795449949,"remaining_time":0.08964767441},
{"learn":[9.105082953],"iteration":8,"passed_time":0.008603447127,"remaining_time":0.08699040984},
{"learn":[8.674157135],"iteration":9,"passed_time":0.00974723239,"remaining_time":0.08772509151},
{"learn":[8.341743544],"iteration":10,"passed_time":0.01103562078,"remaining_time":0.0892882045},
{"learn":[8.049372916],"iteration":11,"passed_time":0.01198342071,"remaining_time":0.08787841851},
{"learn":[7.757318612],"iteration":12,"passed_time":0.01294644824,"remaining_time":0.08664161515},
{"learn":[7.522206899],"iteration":13,"passed_time":0.01401248785,"remaining_time":0.08607671107},
{"learn":[7.297756655],"iteration":14,"passed_time":0.01497870625,"remaining_time":0.08487933544},
{"learn":[7.088359431],"iteration":15,"passed_time":0.01585185787,"remaining_time":0.08322225381},
{"learn":[6.882113791],"iteration":16,"passed_time":0.01664445327,"remaining_time":0.08126409536},
{"learn":[6.704728832],"iteration":17,"passed_time":0.01752691409,"remaining_time":0.07984483085},
{"learn":[6.563881962],"iteration":18,"passed_time":0.01841641945,"remaining_time":0.07851210395},
{"learn":[6.418790279],"iteration":19,"passed_time":0.01930521334,"remaining_time":0.07722085334},
{"learn":[6.315756953],"iteration":20,"passed_time":0.0202033966,"remaining_time":0.07600325387},
{"learn":[6.210157751],"iteration":21,"passed_time":0.02102266751,"remaining_time":0.07453491209},
{"learn":[6.115058449],"iteration":22,"passed_time":0.02187779145,"remaining_time":0.07324304096},
{"learn":[6.014819884],"iteration":23,"passed_time":0.02278397169,"remaining_time":0.0721492437},
{"learn":[5.93117229],"iteration":24,"passed_time":0.02373068509,"remaining_time":0.07119205527},
{"learn":[5.844857622],"iteration":25,"passed_time":0.02462090144,"remaining_time":0.07007487333},
{"learn":[5.771145213],"iteration":26,"passed_time":0.02552699102,"remaining_time":0.06901742015},
{"learn":[5.704018229],"iteration":27,"passed_time":0.02648397561,"remaining_time":0.06810165156},
{"learn":[5.665806474],"iteration":28,"passed_time":0.02731997055,"remaining_time":0.06688682446},
{"learn":[5.616500369],"iteration":29,"passed_time":0.02819910451,"remaining_time":0.06579791052},
{"learn":[5.558023666],"iteration":30,"passed_time":0.02913326248,"remaining_time":0.06484500358},
{"learn":[5.510080976],"iteration":31,"passed_time":0.02999575209,"remaining_time":0.0637409732},
{"learn":[5.468747792],"iteration":32,"passed_time":0.03101590703,"remaining_time":0.06297169002},
{"learn":[5.429275534],"iteration":33,"passed_time":0.03195346152,"remaining_time":0.06202730767},
{"learn":[5.402117324],"iteration":34,"passed_time":0.03282253472,"remaining_time":0.06095613591},
{"learn":[5.367635151],"iteration":35,"passed_time":0.03383135627,"remaining_time":0.06014463337},
{"learn":[5.345181232],"iteration":36,"passed_time":0.03476918085,"remaining_time":0.05920157821},
{"learn":[5.319151269],"iteration":37,"passed_time":0.03565741358,"remaining_time":0.05817788532},
{"learn":[5.296134146],"iteration":38,"passed_time":0.03666046322,"remaining_time":0.05734072453},
{"learn":[5.269629003],"iteration":39,"passed_time":0.03743283737,"remaining_time":0.05614925606},
{"learn":[5.251147059],"iteration":40,"passed_time":0.03819050069,"remaining_time":0.05495706197},
{"learn":[5.248003302],"iteration":41,"passed_time":0.03854969183,"remaining_time":0.05323528872},
{"learn":[5.232376509],"iteration":42,"passed_time":0.03960870647,"remaining_time":0.05250456439},
{"learn":[5.213524255],"iteration":43,"passed_time":0.04080909376,"remaining_time":0.0519388466},
{"learn":[5.189691584],"iteration":44,"passed_time":0.04174889289,"remaining_time":0.05102642464},
{"learn":[5.166052198],"iteration":45,"passed_time":0.04270017571,"remaining_time":0.05012629323},
{"learn":[5.140406659],"iteration":46,"passed_time":0.04358219563,"remaining_time":0.04914588017},
{"learn":[5.118929684],"iteration":47,"passed_time":0.04467226482,"remaining_time":0.04839495355},
{"learn":[5.108792602],"iteration":48,"passed_time":0.04558443694,"remaining_time":0.04744502621},
{"learn":[5.098141225],"iteration":49,"passed_time":0.0464338596,"remaining_time":0.0464338596},
{"learn":[5.085926393],"iteration":50,"passed_time":0.04733579059,"remaining_time":0.04547948508},
{"learn":[5.067816804],"iteration":51,"passed_time":0.04817281767,"remaining_time":0.04446721631},
{"learn":[5.049834901],"iteration":52,"passed_time":0.04909722981,"remaining_time":0.04353905285},
{"learn":[5.03838627],"iteration":53,"passed_time":0.05015068345,"remaining_time":0.04272095257},
{"learn":[5.033534248],"iteration":54,"passed_time":0.05084638846,"remaining_time":0.04160159055},
{"learn":[5.023726885],"iteration":55,"passed_time":0.05188942632,"remaining_time":0.04077026354},
{"learn":[5.01290392],"iteration":56,"passed_time":0.05299370483,"remaining_time":0.03997770715},
{"learn":[5.005569127],"iteration":57,"passed_time":0.0540377438,"remaining_time":0.03913078},
{"learn":[4.989969032],"iteration":58,"passed_time":0.05510001087,"remaining_time":0.03828983806},
{"learn":[4.976762446],"iteration":59,"passed_time":0.05599568896,"remaining_time":0.03733045931},
{"learn":[4.967222715],"iteration":60,"passed_time":0.05692672,"remaining_time":0.0363957718},
{"learn":[4.954407599],"iteration":61,"passed_time":0.05785316157,"remaining_time":0.03545838935},
{"learn":[4.942125056],"iteration":62,"passed_time":0.05865561731,"remaining_time":0.03444853715},
{"learn":[4.930230716],"iteration":63,"passed_time":0.05954485211,"remaining_time":0.03349397931},
{"learn":[4.921695642],"iteration":64,"passed_time":0.06056772265,"remaining_time":0.03261338912},
{"learn":[4.906405625],"iteration":65,"passed_time":0.06156345719,"remaining_time":0.03171450825},
{"learn":[4.894330248],"iteration":66,"passed_time":0.06256637656,"remaining_time":0.03081627502},
{"learn":[4.88211557],"iteration":67,"passed_time":0.06351096558,"remaining_time":0.02988751321},
{"learn":[4.877946398],"iteration":68,"passed_time":0.06444188639,"remaining_time":0.02895215186},
{"learn":[4.863182126],"iteration":69,"passed_time":0.06534352678,"remaining_time":0.02800436862},
{"learn":[4.84646533],"iteration":70,"passed_time":0.06622731033,"remaining_time":0.02705059155},
{"learn":[4.838014752],"iteration":71,"passed_time":0.06714529445,"remaining_time":0.02611205895},
{"learn":[4.82981137],"iteration":72,"passed_time":0.06805254643,"remaining_time":0.02517011991},
{"learn":[4.817094767],"iteration":73,"passed_time":0.06881593156,"remaining_time":0.02417857055},
{"learn":[4.808314151],"iteration":74,"passed_time":0.06956110912,"remaining_time":0.02318703637},
{"learn":[4.796235023],"iteration":75,"passed_time":0.07029667685,"remaining_time":0.02219895058},
{"learn":[4.784434534],"iteration":76,"passed_time":0.07104629356,"remaining_time":0.02122162016},
{"learn":[4.774402487],"iteration":77,"passed_time":0.07173120678,"remaining_time":0.02023187883},
{"learn":[4.76731896],"iteration":78,"passed_time":0.07242235285,"remaining_time":0.01925151152},
{"learn":[4.75934113],"iteration":79,"passed_time":0.07319629977,"remaining_time":0.01829907494},
{"learn":[4.754106378],"iteration":80,"passed_time":0.0738953221,"remaining_time":0.01733347062},
{"learn":[4.744002932],"iteration":81,"passed_time":0.07461380457,"remaining_time":0.01637864003},
{"learn":[4.731700554],"iteration":82,"passed_time":0.07531228578,"remaining_time":0.01542540793},
{"learn":[4.723284153],"iteration":83,"passed_time":0.07606829569,"remaining_time":0.01448919918},
{"learn":[4.712232782],"iteration":84,"passed_time":0.0768704909,"remaining_time":0.01356538075},
{"learn":[4.703046867],"iteration":85,"passed_time":0.07763644132,"remaining_time":0.01263849045},
{"learn":[4.698601855],"iteration":86,"passed_time":0.07838489564,"remaining_time":0.01171268556},
{"learn":[4.692429407],"iteration":87,"passed_time":0.07912492257,"remaining_time":0.01078976217},
{"learn":[4.675027364],"iteration":88,"passed_time":0.07986376706,"remaining_time":0.009870802671},
{"learn":[4.662368584],"iteration":89,"passed_time":0.08065616205,"remaining_time":0.008961795783},
{"learn":[4.646206172],"iteration":90,"passed_time":0.08139808289,"remaining_time":0.008050359846},
{"learn":[4.641245848],"iteration":91,"passed_time":0.08210152433,"remaining_time":0.007139262985},
{"learn":[4.633900435],"iteration":92,"passed_time":0.08283435642,"remaining_time":0.006234844031},
{"learn":[4.624738236],"iteration":93,"passed_time":0.08359457501,"remaining_time":0.005335823937},
{"learn":[4.612798287],"iteration":94,"passed_time":0.08432191577,"remaining_time":0.004437995567},
{"learn":[4.605222001],"iteration":95,"passed_time":0.08510089259,"remaining_time":0.003545870525},
{"learn":[4.601725912],"iteration":96,"passed_time":0.08586740417,"remaining_time":0.002655692912},
{"learn":[4.59722371],"iteration":97,"passed_time":0.08655458205,"remaining_time":0.001766420042},
{"learn":[4.580235665],"iteration":98,"passed_time":0.08724480623,"remaining_time":0.0008812606689},
{"learn":[4.57591791],"iteration":99,"passed_time":0.08793651346,"remaining_time":0}
]}