{
"meta":{"test_sets":[],"test_metrics":[],"learn_metrics":[{"best_value":"Min","name":"RMSE"}],"launch_mode":"Train","parameters":"","iteration_count":100,"learn_sets":["learn"],"name":"experiment"},
"iterations":[
{"learn":[14.005006],"iteration":0,"passed_time":0.001499604866,"remaining_time":0.1484608817},
{"learn":[13.14441192],"iteration":1,"passed_time":0.002905893091,"remaining_time":0.1423887615},
{"learn":[12.34258257],"iteration":2,"passed_time":0.004708830726,"remaining_time":0.1522521935},
{"learn":[11.64527793],"iteration":3,"passed_time":0.007281437623,"remaining_time":0.174754503},
{"learn":[11.02766183],"iteration":4,"passed_time":0.008655627405,"remaining_time":0.1644569207},
{"learn":[10.43485794],"iteration":5,"passed_time":0.01066238615,"remaining_time":0.1670440496},
{"learn":[9.890641275],"iteration":6,"passed_time":0.01221489446,"remaining_time":0.1622835978},
{"learn":[9.492161212],"iteration":7,"passed_time":0.01344973871,"remaining_time":0.1546719952},
{"learn":[9.105082953],"iteration":8,"passed_time":0.01431361746,"remaining_time":0.1447265765},
{"learn":[8.674157135],"iteration":9,"passed_time":0.01509102405,"remaining_time":0.1358192165},
{"learn":[8.341743544],"iteration":10,"passed_time":0.01580654914,"remaining_time":0.1278893522},
{"learn":[8.049372916],"iteration":11,"passed_time":0.0170696036,"remaining_time":0.1251770931},
{"learn":[7.757318612],"iteration":12,"passed_time":0.01969889099,"remaining_time":0.1318310397},
{"learn":[7.522206899],"iteration":13,"passed_time":0.02120978023,"remaining_time":0.13028865},
{"learn":[7.297756655],"iteration":14,"passed_time":0.0226879206,"remaining_time":0.1285648834},
{"learn":[7.088359431],"iteration":15,"passed_time":0.023506073,"remaining_time":0.1234068832},
{"learn":[6.882113791],"iteration":16,"passed_time":0.02429186688,"remaining_time":0.1186014677},
{"learn":[6.704728832],"iteration":17,"passed_time":0.02516716027,"remaining_time":0.1146503968},
{"learn":[6.563881962],"iteration":18,"passed_time":0.02598857911,"remaining_time":0.1107934162},
{"learn":[6.418790279],"iteration":19,"passed_time":0.02674346755,"remaining_time":0.1069738702},
{"learn":[6.315756953],"iteration":20,"passed_time":0.02740528893,"remaining_time":0.1030960869},
{"learn":[6.210157751],"iteration":21,"passed_time":0.02812242743,"remaining_time":0.09970678817},
{"learn":[6.115058449],"iteration":22,"passed_time":0.02879504166,"remaining_time":0.09640079165},
{"learn":[6.014819884],"iteration":23,"passed_time":0.02948865035,"remaining_time":0.09338072609},
{"learn":[5.93117229],"iteration":24,"passed_time":0.03018317096,"remaining_time":0.09054951288},
{"learn":[5.844857622],"iteration":25,"passed_time":0.03118314836,"remaining_time":0.08875203765},
{"learn":[5.771145213],"iteration":26,"passed_time":0.03239102599,"remaining_time":0.08757573693},
{"learn":[5.704018229],"iteration":27,"passed_time":0.03336443714,"remaining_time":0.08579426693},
{"learn":[5.665806474],"iteration":28,"passed_time":0.03425648601,"remaining_time":0.08386932782},
{"learn":[5.616500369],"iteration":29,"passed_time":0.03496142869,"remaining_time":0.08157666695},
{"learn":[5.558023666],"iteration":30,"passed_time":0.03566305435,"remaining_time":0.07937905646},
{"learn":[5.510080976],"iteration":31,"passed_time":0.03637856942,"remaining_time":0.07730446002},
{"learn":[5.468747792],"iteration":32,"passed_time":0.03710520805,"remaining_time":0.07533481633},
{"learn":[5.429275534],"iteration":33,"passed_time":0.03780606207,"remaining_time":0.07338823814},
{"learn":[5.402117324],"iteration":34,"passed_time":0.03854370399,"remaining_time":0.07158116456},
{"learn":[5.367635151],"iteration":35,"passed_time":0.03929246947,"remaining_time":0.06985327905},
{"learn":[5.345181232],"iteration":36,"passed_time":0.04001747463,"remaining_time":0.06813786221},
{"learn":[5.319151269],"iteration":37,"passed_time":0.04081477287,"remaining_time":0.06659252416},
{"learn":[5.296134146],"iteration":38,"passed_time":0.04165863018,"remaining_time":0.06515837028},
{"learn":[5.269629003],"iteration":39,"passed_time":0.04237369429,"remaining_time":0.06356054144},
{"learn":[5.251147059],"iteration":40,"passed_time":0.04304661918,"remaining_time":0.06194513492},
{"learn":[5.248003302],"iteration":41,"passed_time":0.04336348012,"remaining_time":0.05988290111},
{"learn":[5.232376509],"iteration":42,"passed_time":0.04405763997,"remaining_time":0.05840198786},
{"learn":[5.213524255],"iteration":43,"passed_time":0.04475573816,"remaining_time":0.05696184856},
{"learn":[5.189691584],"iteration":44,"passed_time":0.04579309423,"remaining_time":0.0559693374},
{"learn":[5.166052198],"iteration":45,"passed_time":0.04745566465,"remaining_time":0.05570882372},
{"learn":[5.140406659],"iteration":46,"passed_time":0.04940799862,"remaining_time":0.0557154027},
{"learn":[5.118929684],"iteration":47,"passed_time":0.05088561741,"remaining_time":0.05512608553},
{"learn":[5.108792602],"iteration":48,"passed_time":0.05184785538,"remaining_time":0.05396409437},
{"learn":[5.098141225],"iteration":49,"passed_time":0.05272593467,"remaining_time":0.05272593467},
{"learn":[5.085926393],"iteration":50,"passed_time":0.0535517428,"remaining_time":0.05145167446},
{"learn":[5.067816804],"iteration":51,"passed_time":0.05444790085,"remaining_time":0.05025960079},
{"learn":[5.049834901],"iteration":52,"passed_time":0.05535653437,"remaining_time":0.04908975689},
{"learn":[5.03838627],"iteration":53,"passed_time":0.05609022793,"remaining_time":0.04778056453},
{"learn":[5.033534248],"iteration":54,"passed_time":0.05655498202,"remaining_time":0.04627225802},
{"learn":[5.023726885],"iteration":55,"passed_time":0.05729286445,"remaining_time":0.04501582207},
{"learn":[5.01290392],"iteration":56,"passed_time":0.05801045391,"remaining_time":0.04376227225},
{"learn":[5.005569127],"iteration":57,"passed_time":0.0588400305,"remaining_time":0.04260829795},
{"learn":[4.989969032],"iteration":58,"passed_time":0.05987407051,"remaining_time":0.04160740493},
{"learn":[4.976762446],"iteration":59,"passed_time":0.06121315596,"remaining_time":0.04080877064},
{"learn":[4.967222715],"iteration":60,"passed_time":0.06317149217,"remaining_time":0.04038833106},
{"learn":[4.954407599],"iteration":61,"passed_time":0.0658086863,"remaining_time":0.04033435612},
{"learn":[4.942125056],"iteration":62,"passed_time":0.06695435267,"remaining_time":0.0393223976},
{"learn":[4.930230716],"iteration":63,"passed_time":0.06783036712,"remaining_time":0.0381545815},
{"learn":[4.921695642],"iteration":64,"passed_time":0.06870990998,"remaining_time":0.03699764384},
{"learn":[4.906405625],"iteration":65,"passed_time":0.06952576752,"remaining_time":0.03581630448},
{"learn":[4.894330248],"iteration":66,"passed_time":0.07028443396,"remaining_time":0.03461770628},
{"learn":[4.88211557],"iteration":67,"passed_time":0.07098991779,"remaining_time":0.03340702014},
{"learn":[4.877946398],"iteration":68,"passed_time":0.07170614437,"remaining_time":0.03221580399},
{"learn":[4.863182126],"iteration":69,"passed_time":0.07244050935,"remaining_time":0.03104593258},
{"learn":[4.84646533],"iteration":70,"passed_time":0.07342006303,"remaining_time":0.02998847645},
{"learn":[4.838014752],"iteration":71,"passed_time":0.07453627704,"remaining_time":0.02898632996},
{"learn":[4.82981137],"iteration":72,"passed_time":0.07678199176,"remaining_time":0.02839881887},
{"learn":[4.817094767],"iteration":73,"passed_time":0.07991521669,"remaining_time":0.02807831938},
{"learn":[4.808314151],"iteration":74,"passed_time":0.08122312565,"remaining_time":0.02707437522},
{"learn":[4.796235023],"iteration":75,"passed_time":0.08221375373,"remaining_time":0.02596223802},
{"learn":[4.784434534],"iteration":76,"passed_time":0.08330437307,"remaining_time":0.02488312442},
{"learn":[4.774402487],"iteration":77,"passed_time":0.08421722551,"remaining_time":0.02375357643},
{"learn":[4.76731896],"iteration":78,"passed_time":0.0849899417,"remaining_time":0.02259226298},
{"learn":[4.75934113],"iteration":79,"passed_time":0.085755623,"remaining_time":0.02143890575},
{"learn":[4.754106378],"iteration":80,"passed_time":0.08652066293,"remaining_time":0.02029497032},
{"learn":[4.744002932],"iteration":81,"passed_time":0.08737282687,"remaining_time":0.01917940102},
{"learn":[4.731700554],"iteration":82,"passed_time":0.08810798353,"remaining_time":0.01804621349},
{"learn":[4.723284153],"iteration":83,"passed_time":0.088817075,"remaining_time":0.0169175381},
{"learn":[4.712232782],"iteration":84,"passed_time":0.09002394096,"remaining_time":0.01588657782},
{"learn":[4.703046867],"iteration":85,"passed_time":0.09178624255,"remaining_time":0.01494194646},
{"learn":[4.698601855],"iteration":86,"passed_time":0.09421637825,"remaining_time":0.01407830939},
{"learn":[4.692429407],"iteration":87,"passed_time":0.09515793194,"remaining_time":0.01297608163},
{"learn":[4.675027364],"iteration":88,"passed_time":0.09614900096,"remaining_time":0.01188358439},
{"learn":[4.662368584],"iteration":89,"passed_time":0.09709171712,"remaining_time":0.01078796857},
{"learn":[4.646206172],"iteration":90,"passed_time":0.09779128842,"remaining_time":0.009671665888},
{"learn":[4.641245848],"iteration":91,"passed_time":0.0984444214,"remaining_time":0.00856038447},
{"learn":[4.633900435],"iteration":92,"passed_time":0.09910635301,"remaining_time":0.007459617969},
{"learn":[4.624738236],"iteration":93,"passed_time":0.09986124145,"remaining_time":0.006374121795},
{"learn":[4.612798287],"iteration":94,"passed_time":0.1006921905,"remaining_time":0.005299588972},
{"learn":[4.605222001],"iteration":95,"passed_time":0.1013721903,"remaining_time":0.004223841264},
{"learn":[4.601725912],"iteration":96,"passed_time":0.1020910325,"remaining_time":0.003157454612},
{"learn":[4.59722371],"iteration":97,"passed_time":0.1027849819,"remaining_time":0.002097652691},
{"learn":[4.580235665],"iteration":98,"passed_time":0.1034746322,"remaining_time":0.001045198305},
{"learn":[4.57591791],"iteration":99,"passed_time":0.1046720977,"remaining_time":0}
]}